src/bitable_mcp/__init__.py
src/bitable_mcp/cli.py
src/bitable_mcp/server.py
orange1_bitable_mcp-0.2.1.dist-info/METADATA
orange1_bitable_mcp-0.2.1.dist-info/WHEEL
orange1_bitable_mcp-0.2.1.dist-info/entry_points.txt
orange1_bitable_mcp-0.2.1.dist-info/RECORD
